{"v":"5.7.1","fr":60,"ip":0,"op":120,"w":512,"h":512,"nm":"Comp 1","ddd":0,"assets":[],"layers":[{"ddd":0,"ind":1,"ty":4,"nm":"Shape Layer 1","sr":1,"ks":{"o":{"a":0,"k":100,"ix":11},"r":{"a":0,"k":0,"ix":10},"p":{"a":1,"k":[{"i":{"x":0.317,"y":1},"o":{"x":0.532,"y":0},"t":17,"s":[256,372,0],"to":[0,0,0],"ti":[0,0,0]},{"t":24,"s":[256,253,0]}],"ix":2},"a":{"a":0,"k":[0,0,0],"ix":1},"s":{"a":0,"k":[100,100,100],"ix":6}},"ao":0,"shapes":[{"ty":"gr","it":[{"ind":0,"ty":"sh","ix":1,"ks":{"a":0,"k":{"i":[[0,0],[0,0]],"o":[[0,0],[0,0]],"v":[[-2,-186],[-2.334,-263.997]],"c":false},"ix":2},"nm":"Path 1","mn":"ADBE Vector Shape - Group","hd":false},{"ty":"st","c":{"a":0,"k":[1,1,1,1],"ix":3},"o":{"a":0,"k":100,"ix":4},"w":{"a":0,"k":16,"ix":5},"lc":2,"lj":1,"ml":4,"bm":0,"nm":"Stroke 1","mn":"ADBE Vector Graphic - Stroke","hd":false},{"ty":"tr","p":{"a":0,"k":[90,-67],"ix":2},"a":{"a":0,"k":[0,-187],"ix":1},"s":{"a":0,"k":[100,100],"ix":3},"r":{"a":0,"k":90.869,"ix":6},"o":{"a":0,"k":100,"ix":7},"sk":{"a":0,"k":0,"ix":4},"sa":{"a":0,"k":0,"ix":5},"nm":"Transform"}],"nm":"Shape 5","np":2,"cix":2,"bm":0,"ix":1,"mn":"ADBE Vector Group","hd":false},{"ty":"gr","it":[{"ind":0,"ty":"sh","ix":1,"ks":{"a":0,"k":{"i":[[0,0],[0,0]],"o":[[0,0],[0,0]],"v":[[-2,-186],[-2.12,-259]],"c":false},"ix":2},"nm":"Path 1","mn":"ADBE Vector Shape - Group","hd":false},{"ty":"st","c":{"a":0,"k":[1,1,1,1],"ix":3},"o":{"a":0,"k":100,"ix":4},"w":{"a":0,"k":16,"ix":5},"lc":2,"lj":1,"ml":4,"bm":0,"nm":"Stroke 1","mn":"ADBE Vector Graphic - Stroke","hd":false},{"ty":"tr","p":{"a":0,"k":[-90,-67],"ix":2},"a":{"a":0,"k":[0,-187],"ix":1},"s":{"a":0,"k":[100,100],"ix":3},"r":{"a":0,"k":-89.597,"ix":6},"o":{"a":0,"k":100,"ix":7},"sk":{"a":0,"k":0,"ix":4},"sa":{"a":0,"k":0,"ix":5},"nm":"Transform"}],"nm":"Shape 4","np":2,"cix":2,"bm":0,"ix":2,"mn":"ADBE Vector Group","hd":false},{"ty":"gr","it":[{"ind":0,"ty":"sh","ix":1,"ks":{"a":0,"k":{"i":[[0,0],[0,0]],"o":[[0,0],[0,0]],"v":[[-7.882,-177.913],[-23.321,-250.087]],"c":false},"ix":2},"nm":"Path 1","mn":"ADBE Vector Shape - Group","hd":false},{"ty":"st","c":{"a":0,"k":[1,1,1,1],"ix":3},"o":{"a":0,"k":100,"ix":4},"w":{"a":0,"k":16,"ix":5},"lc":2,"lj":1,"ml":4,"bm":0,"nm":"Stroke 1","mn":"ADBE Vector Graphic - Stroke","hd":false},{"ty":"tr","p":{"a":0,"k":[-80,-157],"ix":2},"a":{"a":0,"k":[0,-187],"ix":1},"s":{"a":0,"k":[100,100],"ix":3},"r":{"a":0,"k":-36.027,"ix":6},"o":{"a":0,"k":100,"ix":7},"sk":{"a":0,"k":0,"ix":4},"sa":{"a":0,"k":0,"ix":5},"nm":"Transform"}],"nm":"Shape 3","np":2,"cix":2,"bm":0,"ix":3,"mn":"ADBE Vector Group","hd":false},{"ty":"gr","it":[{"ind":0,"ty":"sh","ix":1,"ks":{"a":0,"k":{"i":[[0,0],[0,0]],"o":[[0,0],[0,0]],"v":[[4.459,-178.366],[19.316,-250.867]],"c":false},"ix":2},"nm":"Path 1","mn":"ADBE Vector Shape - Group","hd":false},{"ty":"st","c":{"a":0,"k":[1,1,1,1],"ix":3},"o":{"a":0,"k":100,"ix":4},"w":{"a":0,"k":16,"ix":5},"lc":2,"lj":1,"ml":4,"bm":0,"nm":"Stroke 1","mn":"ADBE Vector Graphic - Stroke","hd":false},{"ty":"tr","p":{"a":0,"k":[80,-157],"ix":2},"a":{"a":0,"k":[0,-187],"ix":1},"s":{"a":0,"k":[100,100],"ix":3},"r":{"a":0,"k":40.236,"ix":6},"o":{"a":0,"k":100,"ix":7},"sk":{"a":0,"k":0,"ix":4},"sa":{"a":0,"k":0,"ix":5},"nm":"Transform"}],"nm":"Shape 2","np":2,"cix":2,"bm":0,"ix":4,"mn":"ADBE Vector Group","hd":false},{"ty":"gr","it":[{"ind":0,"ty":"sh","ix":1,"ks":{"a":0,"k":{"i":[[0,0],[0,0]],"o":[[0,0],[0,0]],"v":[[-2,-186],[-1,-243.5]],"c":false},"ix":2},"nm":"Path 1","mn":"ADBE Vector Shape - Group","hd":false},{"ty":"st","c":{"a":0,"k":[1,1,1,1],"ix":3},"o":{"a":0,"k":100,"ix":4},"w":{"a":0,"k":16,"ix":5},"lc":2,"lj":1,"ml":4,"bm":0,"nm":"Stroke 1","mn":"ADBE Vector Graphic - Stroke","hd":false},{"ty":"tr","p":{"a":0,"k":[0,-187],"ix":2},"a":{"a":0,"k":[0,-187],"ix":1},"s":{"a":0,"k":[100,100],"ix":3},"r":{"a":0,"k":0,"ix":6},"o":{"a":0,"k":100,"ix":7},"sk":{"a":0,"k":0,"ix":4},"sa":{"a":0,"k":0,"ix":5},"nm":"Transform"}],"nm":"Shape 1","np":2,"cix":2,"bm":0,"ix":5,"mn":"ADBE Vector Group","hd":false},{"ty":"tm","s":{"a":1,"k":[{"i":{"x":[0.4],"y":[1]},"o":{"x":[0.33],"y":[0]},"t":20,"s":[0]},{"t":30,"s":[100]}],"ix":1},"e":{"a":1,"k":[{"i":{"x":[0.4],"y":[1]},"o":{"x":[0.33],"y":[0]},"t":17,"s":[0]},{"t":27,"s":[100]}],"ix":2},"o":{"a":0,"k":0,"ix":3},"m":1,"ix":6,"nm":"Trim Paths 1","mn":"ADBE Vector Filter - Trim","hd":false}],"ip":18,"op":31,"st":-1,"bm":0},{"ddd":0,"ind":2,"ty":4,"nm":"Top","parent":3,"sr":1,"ks":{"o":{"a":0,"k":100,"ix":11},"r":{"a":1,"k":[{"i":{"x":[0.382],"y":[1]},"o":{"x":[0.534],"y":[0]},"t":3,"s":[0]},{"t":18,"s":[180]}],"ix":10},"p":{"a":1,"k":[{"i":{"x":0.2,"y":1},"o":{"x":0.4,"y":0},"t":2,"s":[-1.293,-17.921,0],"to":[0,0,0],"ti":[0,0,0]},{"i":{"x":0.4,"y":1},"o":{"x":0.31,"y":0},"t":12,"s":[-1.293,-123.921,0],"to":[0,0,0],"ti":[0,0,0]},{"i":{"x":0.69,"y":1},"o":{"x":0.31,"y":0},"t":18,"s":[-1.293,-46.921,0],"to":[0,0,0],"ti":[0,0,0]},{"i":{"x":0.69,"y":1},"o":{"x":0.31,"y":0},"t":23,"s":[-1.293,-63.921,0],"to":[0,0,0],"ti":[0,0,0]},{"i":{"x":0.69,"y":1},"o":{"x":0.167,"y":0},"t":28,"s":[-1.293,-52.921,0],"to":[0,0,0],"ti":[0,0,0]},{"t":32,"s":[-1.293,-57.921,0]}],"ix":2},"a":{"a":0,"k":[172.332,-134.171,0],"ix":1},"s":{"a":0,"k":[100,100,100],"ix":6}},"ao":0,"shapes":[{"ty":"gr","it":[{"ind":0,"ty":"sh","ix":1,"ks":{"a":1,"k":[{"i":{"x":0.1,"y":1},"o":{"x":0.35,"y":0},"t":3,"s":[{"i":[[-60.047,-1.953],[-7.601,8.812],[11.216,6.808],[60.074,-0.721],[8.451,-1.873],[-9.93,-10.711]],"o":[[60.047,1.953],[7.601,-8.812],[-11.346,-6.887],[-60.16,0.722],[-8.451,1.873],[9.93,10.711]],"v":[[171.71,-35.897],[306.13,-57.407],[300.717,-77.461],[173.346,-86.203],[47.99,-78.856],[38.107,-55.969]],"c":true}]},{"i":{"x":0.65,"y":1},"o":{"x":0.35,"y":0},"t":15,"s":[{"i":[[-27.519,0],[0,27.521],[0,0],[27.519,0],[0,-27.521],[0,0]],"o":[[27.519,0],[0,0],[0,-27.521],[-27.519,0],[0,0],[0,27.521]],"v":[[172.332,-34.697],[222.065,-84.434],[222.065,-183.908],[172.332,-233.645],[122.599,-183.908],[122.599,-84.434]],"c":true}]},{"i":{"x":0.65,"y":1},"o":{"x":0.35,"y":0},"t":19,"s":[{"i":[[-36.915,0],[-4.805,15.85],[7.712,20.051],[36.915,0],[6.531,-18.949],[-5.986,-14.65]],"o":[[36.915,0],[4.805,-15.85],[-7.712,-20.051],[-36.915,0],[-6.531,18.949],[5.986,14.65]],"v":[[172.284,-91.046],[238.998,-126.696],[238.998,-197.995],[172.284,-233.645],[105.57,-197.995],[105.57,-126.696]],"c":true}]},{"i":{"x":0.65,"y":1},"o":{"x":0.35,"y":0},"t":24,"s":[{"i":[[-26.398,0],[0,29.885],[0,0],[26.398,0],[0,-29.885],[0,0]],"o":[[26.398,0],[0,0],[0,-29.885],[-26.398,0],[0,0],[0,29.885]],"v":[[172.332,-26.155],[220.04,-80.163],[220.04,-188.179],[172.332,-242.188],[124.625,-188.179],[124.625,-80.163]],"c":true}]},{"i":{"x":0.65,"y":1},"o":{"x":0.35,"y":0},"t":29,"s":[{"i":[[-28.659,0],[0,25.792],[0,0],[28.659,0],[0,-25.792],[0,0]],"o":[[28.659,0],[0,0],[0,-25.792],[-28.659,0],[0,0],[0,25.792]],"v":[[172.332,-47.194],[224.125,-93.807],[224.125,-187.032],[172.332,-233.645],[120.54,-187.032],[120.54,-93.807]],"c":true}]},{"t":33,"s":[{"i":[[-27.519,0],[0,27.521],[0,0],[27.519,0],[0,-27.521],[0,0]],"o":[[27.519,0],[0,0],[0,-27.521],[-27.519,0],[0,0],[0,27.521]],"v":[[172.332,-34.697],[222.065,-84.434],[222.065,-183.908],[172.332,-233.645],[122.599,-183.908],[122.599,-84.434]],"c":true}]}],"ix":2},"nm":"Path 1","mn":"ADBE Vector Shape - Group","hd":false},{"ty":"fl","c":{"a":0,"k":[1,1,1,1],"ix":4},"o":{"a":0,"k":100,"ix":5},"r":1,"bm":0,"nm":"Fill 1","mn":"ADBE Vector Graphic - Fill","hd":false},{"ty":"tr","p":{"a":0,"k":[0,0],"ix":2},"a":{"a":0,"k":[0,0],"ix":1},"s":{"a":0,"k":[100,100],"ix":3},"r":{"a":0,"k":0,"ix":6},"o":{"a":0,"k":100,"ix":7},"sk":{"a":0,"k":0,"ix":4},"sa":{"a":0,"k":0,"ix":5},"nm":"Transform"}],"nm":"Group 1","np":2,"cix":2,"bm":0,"ix":1,"mn":"ADBE Vector Group","hd":false}],"ip":0,"op":120,"st":0,"bm":0},{"ddd":0,"ind":3,"ty":4,"nm":"Middle","parent":4,"sr":1,"ks":{"o":{"a":0,"k":100,"ix":11},"r":{"a":0,"k":0,"ix":10},"p":{"a":0,"k":[-1.333,91.333,0],"ix":2},"a":{"a":0,"k":[-1.333,91.333,0],"ix":1},"s":{"a":0,"k":[100,100,100],"ix":6}},"ao":0,"shapes":[{"ty":"gr","it":[{"ind":0,"ty":"sh","ix":1,"ks":{"a":1,"k":[{"i":{"x":0.833,"y":0.833},"o":{"x":0.4,"y":0},"t":3,"s":[{"i":[[0,0],[-101.927,0],[0,0]],"o":[[0,0],[106.064,0],[0,0]],"v":[[-128.61,52.347],[-2.924,91.334],[125.943,52.347]],"c":false}]},{"i":{"x":0.2,"y":1},"o":{"x":0.167,"y":0.167},"t":6,"s":[{"i":[[0,0],[-93.549,0.001],[0,0]],"o":[[0,0],[97.346,-0.001],[0,0]],"v":[[-130.147,55.017],[-2.794,91.334],[127.481,54.017]],"c":false}]},{"i":{"x":0.4,"y":1},"o":{"x":0.31,"y":0},"t":14,"s":[{"i":[[0,0],[-73.41,0.001],[0,0]],"o":[[0,0],[76.39,-0.001],[0,0]],"v":[[-93,-16.848],[-2.479,91.333],[90.333,-16.848]],"c":false}]},{"i":{"x":0.69,"y":1},"o":{"x":0.31,"y":0},"t":20,"s":[{"i":[[0,0],[-83.212,1.774],[0,0]],"o":[[0,0],[82.815,-1.765],[0,0]],"v":[[-117.667,30.388],[-2.788,91.334],[115,30.388]],"c":false}]},{"i":{"x":0.67,"y":1},"o":{"x":0.31,"y":0},"t":25,"s":[{"i":[[0,0],[-75.011,0.001],[0,0]],"o":[[0,0],[78.056,-0.001],[0,0]],"v":[[-95,0.091],[-2.504,91.333],[92.333,0.091]],"c":false}]},{"i":{"x":0.67,"y":1},"o":{"x":0.33,"y":0},"t":30,"s":[{"i":[[0,0],[-84.354,0.001],[0,0]],"o":[[0,0],[87.778,-0.001],[0,0]],"v":[[-106.667,13.292],[-2.65,91.333],[104,13.292]],"c":false}]},{"t":34,"s":[{"i":[[0,0],[-80.083,0.001],[0,0]],"o":[[0,0],[83.334,-0.001],[0,0]],"v":[[-101.333,7.5],[-2.583,91.333],[98.667,7.5]],"c":false}]}],"ix":2},"nm":"Path 1","mn":"ADBE Vector Shape - Group","hd":false},{"ty":"st","c":{"a":0,"k":[1,1,1,1],"ix":3},"o":{"a":0,"k":100,"ix":4},"w":{"a":0,"k":32,"ix":5},"lc":2,"lj":2,"bm":0,"nm":"Stroke 1","mn":"ADBE Vector Graphic - Stroke","hd":false},{"ty":"tr","p":{"a":0,"k":[0,0],"ix":2},"a":{"a":0,"k":[0,0],"ix":1},"s":{"a":0,"k":[100,100],"ix":3},"r":{"a":0,"k":0,"ix":6},"o":{"a":0,"k":100,"ix":7},"sk":{"a":0,"k":0,"ix":4},"sa":{"a":0,"k":0,"ix":5},"nm":"Transform"}],"nm":"Group 1","np":2,"cix":2,"bm":0,"ix":1,"mn":"ADBE Vector Group","hd":false}],"ip":0,"op":120,"st":0,"bm":0},{"ddd":0,"ind":4,"ty":4,"nm":"Bottom","sr":1,"ks":{"o":{"a":0,"k":100,"ix":11},"r":{"a":0,"k":0,"ix":10},"p":{"a":1,"k":[{"i":{"x":0.2,"y":1},"o":{"x":0.4,"y":0},"t":0,"s":[254.667,507.25,0],"to":[0,0,0],"ti":[0,0,0]},{"i":{"x":0.4,"y":1},"o":{"x":0.31,"y":0},"t":11,"s":[254.667,363.25,0],"to":[0,0,0],"ti":[0,0,0]},{"i":{"x":0.69,"y":1},"o":{"x":0.31,"y":0},"t":17,"s":[254.667,457.25,0],"to":[0,0,0],"ti":[0,0,0]},{"i":{"x":0.68,"y":1},"o":{"x":0.31,"y":0},"t":22,"s":[254.667,376.25,0],"to":[0,0,0],"ti":[0,0,0]},{"i":{"x":0.68,"y":1},"o":{"x":0.32,"y":0},"t":27,"s":[254.667,411.25,0],"to":[0,0,0],"ti":[0,0,0]},{"i":{"x":0.68,"y":1},"o":{"x":0.32,"y":0},"t":32,"s":[254.667,391.75,0],"to":[0,0,0],"ti":[0,0,0]},{"t":36,"s":[254.667,397.25,0]}],"ix":2},"a":{"a":0,"k":[-1.333,141.25,0],"ix":1},"s":{"a":1,"k":[{"i":{"x":[0.2,0.2,0.2],"y":[1,1,1]},"o":{"x":[0.32,0.32,0.32],"y":[0,0,0]},"t":0,"s":[0,0,100]},{"t":5,"s":[100,100,100]}],"ix":6}},"ao":0,"shapes":[{"ty":"gr","it":[{"ind":0,"ty":"sh","ix":1,"ks":{"a":0,"k":{"i":[[0,0],[0,0]],"o":[[0,0],[0,0]],"v":[[-1.333,141.25],[-1.333,96.333]],"c":false},"ix":2},"nm":"Path 1","mn":"ADBE Vector Shape - Group","hd":false},{"ty":"st","c":{"a":0,"k":[1,1,1,1],"ix":3},"o":{"a":0,"k":100,"ix":4},"w":{"a":0,"k":33,"ix":5},"lc":2,"lj":2,"bm":0,"nm":"Stroke 1","mn":"ADBE Vector Graphic - Stroke","hd":false},{"ty":"tr","p":{"a":0,"k":[0,0],"ix":2},"a":{"a":0,"k":[0,0],"ix":1},"s":{"a":0,"k":[100,100],"ix":3},"r":{"a":0,"k":0,"ix":6},"o":{"a":0,"k":100,"ix":7},"sk":{"a":0,"k":0,"ix":4},"sa":{"a":0,"k":0,"ix":5},"nm":"Transform"}],"nm":"Group 1","np":2,"cix":2,"bm":0,"ix":1,"mn":"ADBE Vector Group","hd":false}],"ip":0,"op":120,"st":0,"bm":0}],"markers":[{"tm":0,"cm":"1","dr":0},{"tm":45,"cm":"2","dr":0}]}