{"v":"5.7.1","fr":60,"ip":0,"op":36,"w":512,"h":512,"nm":"Comp 1","ddd":0,"assets":[],"layers":[{"ddd":0,"ind":1,"ty":3,"nm":"Null 2","sr":1,"ks":{"o":{"a":0,"k":0,"ix":11},"r":{"a":0,"k":0,"ix":10},"p":{"a":0,"k":[256,256,0],"ix":2},"a":{"a":0,"k":[0,0,0],"ix":1},"s":{"a":0,"k":[120,120,100],"ix":6}},"ao":0,"ip":0,"op":120,"st":0,"bm":0},{"ddd":0,"ind":2,"ty":4,"nm":"Head 2","parent":3,"sr":1,"ks":{"o":{"a":0,"k":100,"ix":11},"r":{"a":0,"k":0,"ix":10},"p":{"a":0,"k":[-8.429,-38.524,0],"ix":2},"a":{"a":0,"k":[-8.429,-38.524,0],"ix":1},"s":{"a":0,"k":[100,100,100],"ix":6}},"ao":0,"shapes":[{"ty":"gr","it":[{"ind":0,"ty":"sh","ix":1,"ks":{"a":1,"k":[{"i":{"x":0.3,"y":1},"o":{"x":0.4,"y":0},"t":0,"s":[{"i":[[-21.723,0],[0,-21.723],[21.723,0],[0,21.723]],"o":[[21.723,0],[0,21.723],[-21.723,0],[0,-21.723]],"v":[[-8.429,-77.857],[30.905,-38.524],[-8.429,0.81],[-47.762,-38.524]],"c":true}]},{"i":{"x":0.3,"y":1},"o":{"x":0.3,"y":0},"t":7.414,"s":[{"i":[[-23.783,0],[0,-11.771],[23.783,0],[0,11.771]],"o":[[23.783,0],[0,11.771],[-23.783,0],[0,-11.771]],"v":[[-5.479,-14.693],[37.585,6.621],[-5.479,27.935],[-48.543,6.621]],"c":true}]},{"t":14.830078125,"s":[{"i":[[-17.964,0],[0,-22.456],[17.964,0],[0,22.456]],"o":[[17.964,0],[0,22.456],[-17.964,0],[0,-22.456]],"v":[[2.11,-175.185],[34.636,-134.525],[2.11,-93.865],[-30.417,-134.525]],"c":true}]}],"ix":2},"nm":"Path 1","mn":"ADBE Vector Shape - Group","hd":false},{"ty":"fl","c":{"a":0,"k":[1,1,1,1],"ix":4},"o":{"a":0,"k":100,"ix":5},"r":1,"bm":0,"nm":"Fill 1","mn":"ADBE Vector Graphic - Fill","hd":false},{"ty":"tr","p":{"a":0,"k":[0,0],"ix":2},"a":{"a":0,"k":[0,0],"ix":1},"s":{"a":0,"k":[100,100],"ix":3},"r":{"a":0,"k":0,"ix":6},"o":{"a":0,"k":100,"ix":7},"sk":{"a":0,"k":0,"ix":4},"sa":{"a":0,"k":0,"ix":5},"nm":"Transform"}],"nm":"Group 1","np":2,"cix":2,"bm":0,"ix":1,"mn":"ADBE Vector Group","hd":false}],"ip":0,"op":15,"st":-51,"bm":0},{"ddd":0,"ind":3,"ty":4,"nm":"Body 2","parent":1,"sr":1,"ks":{"o":{"a":0,"k":100,"ix":11},"r":{"a":1,"k":[{"i":{"x":[0.3],"y":[1]},"o":{"x":[0.4],"y":[0]},"t":1.854,"s":[0]},{"i":{"x":[0.3],"y":[1]},"o":{"x":[0.3],"y":[0]},"t":9.268,"s":[-8]},{"t":16.68359375,"s":[2]}],"ix":10},"p":{"a":1,"k":[{"i":{"x":0.3,"y":1},"o":{"x":0.4,"y":0},"t":0,"s":[-8.429,73.857,0],"to":[0,0,0],"ti":[0,0,0]},{"i":{"x":0.3,"y":1},"o":{"x":0.3,"y":0},"t":7.414,"s":[-8.429,108.857,0],"to":[0,0,0],"ti":[0,0,0]},{"t":15,"s":[-12.179,53.857,0]}],"ix":2},"a":{"a":0,"k":[-8.429,73.857,0],"ix":1},"s":{"a":0,"k":[100,100,100],"ix":6}},"ao":0,"shapes":[{"ty":"gr","it":[{"ind":0,"ty":"sh","ix":1,"ks":{"a":1,"k":[{"i":{"x":0.3,"y":1},"o":{"x":0.4,"y":0},"t":0,"s":[{"i":[[0,0],[0,0],[0,-22.167],[0,0],[4.483,0],[0,0],[0,4.483],[0,0],[-47.453,0.354]],"o":[[0,0],[48.466,0],[0,0],[0,4.483],[0,0],[-4.483,0],[0,0],[0,-21.945],[0,0]],"v":[[-9.875,17.672],[-8.429,17.667],[61.81,57.803],[61.81,65.74],[53.692,73.857],[-70.549,73.857],[-78.667,65.74],[-78.667,57.803],[-9.875,17.672]],"c":true}]},{"i":{"x":0.833,"y":0.82},"o":{"x":0.3,"y":0},"t":7.414,"s":[{"i":[[0,0],[0,0],[0,-8.968],[0,0],[10.089,-0.439],[0,0],[0,1.814],[0,0],[-51.235,0.143]],"o":[[0,0],[52.328,0],[0,0],[0,1.814],[0,0],[-7.526,-0.95],[0,0],[0,-8.878],[0,0]],"v":[[-8.471,47.293],[-6.91,47.291],[68.115,60.142],[68.115,63.353],[53.999,68.952],[-71.652,69.577],[-83.556,63.353],[-83.556,60.142],[-8.471,47.293]],"c":true}]},{"i":{"x":0.3,"y":1},"o":{"x":0.167,"y":0.18},"t":10.195,"s":[{"i":[[0,0],[0,0],[0.627,-17.978],[0,0],[8.234,-4.779],[4.916,8.584],[1.556,6.714],[0,0],[-47.495,0.938]],"o":[[0,0],[48.687,-2.133],[0,0],[-1.939,6.17],[-9.891,8.711],[-4.408,-2.194],[0,0],[-2.459,-17.223],[0,0]],"v":[[0.129,-19.016],[3.589,-19.222],[57.088,51.783],[53.89,65.519],[36.027,81.999],[-41.386,79.436],[-52.042,64.203],[-55.017,50.49],[-4.942,-18.815]],"c":true}]},{"t":14.830078125,"s":[{"i":[[0,0],[0,0],[4.484,-25.333],[0,0],[5.619,-9.118],[8.961,15.647],[2.837,10.745],[0,0],[-37.94,2.083]],"o":[[0,0],[36.927,0.974],[0,0],[-3.534,9.754],[-7.022,11.394],[-1.843,-3.218],[0,0],[-3.147,-27.7],[0,0]],"v":[[3.796,-72.739],[8.817,-73.113],[37.69,33.503],[30.931,56.395],[16.636,87.276],[-17.203,84.22],[-29.428,59.84],[-31.998,38.356],[-10.61,-71.295]],"c":true}]}],"ix":2},"nm":"Path 1","mn":"ADBE Vector Shape - Group","hd":false},{"ty":"fl","c":{"a":0,"k":[1,1,1,1],"ix":4},"o":{"a":0,"k":100,"ix":5},"r":1,"bm":0,"nm":"Fill 1","mn":"ADBE Vector Graphic - Fill","hd":false},{"ty":"tr","p":{"a":0,"k":[0,0],"ix":2},"a":{"a":0,"k":[0,0],"ix":1},"s":{"a":0,"k":[100,100],"ix":3},"r":{"a":0,"k":0,"ix":6},"o":{"a":0,"k":100,"ix":7},"sk":{"a":0,"k":0,"ix":4},"sa":{"a":0,"k":0,"ix":5},"nm":"Transform"}],"nm":"Shape","np":2,"cix":2,"bm":0,"ix":1,"mn":"ADBE Vector Group","hd":false}],"ip":0,"op":15,"st":-51,"bm":0},{"ddd":0,"ind":4,"ty":4,"nm":"Plus 2","parent":3,"sr":1,"ks":{"o":{"a":0,"k":100,"ix":11},"r":{"a":1,"k":[{"i":{"x":[0.733],"y":[0.837]},"o":{"x":[0.413],"y":[0]},"t":0,"s":[90]},{"i":{"x":[0.638],"y":[1]},"o":{"x":[0.417],"y":[-0.08]},"t":5.561,"s":[76.14]},{"t":13.90234375,"s":[142]}],"ix":10},"p":{"a":1,"k":[{"i":{"x":0.833,"y":1},"o":{"x":0.31,"y":0},"t":0.928,"s":[84.509,-3.613,0],"to":[0,0,0],"ti":[0,0,0]},{"i":{"x":0.535,"y":0.604},"o":{"x":0.417,"y":0},"t":5.561,"s":[83.787,7.318,0],"to":[0,0,0],"ti":[13.308,-11.065,0]},{"i":{"x":0.535,"y":1},"o":{"x":0.226,"y":0.077},"t":10.195,"s":[55.242,26.612,0],"to":[-3.001,2.495,0],"ti":[2.608,-2.722,0]},{"t":13.90234375,"s":[45.766,-41.188,0]}],"ix":2},"a":{"a":0,"k":[-50.491,-44.113,0],"ix":1},"s":{"a":1,"k":[{"i":{"x":[0.614,0.614,0.29],"y":[1,1,1]},"o":{"x":[0.31,0.31,0.31],"y":[0,0,0]},"t":6.488,"s":[100,100,100]},{"t":12.9765625,"s":[0,0,100]}],"ix":6}},"ao":0,"shapes":[{"ty":"gr","it":[{"ind":0,"ty":"sh","ix":1,"ks":{"a":0,"k":{"i":[[0,0],[0,0]],"o":[[0,0],[0,0]],"v":[[-78.417,-44.113],[-22.565,-44.113]],"c":false},"ix":2},"nm":"Path 1","mn":"ADBE Vector Shape - Group","hd":false},{"ty":"st","c":{"a":0,"k":[1,1,1,1],"ix":3},"o":{"a":0,"k":100,"ix":4},"w":{"a":0,"k":14,"ix":5},"lc":2,"lj":1,"ml":4,"bm":0,"nm":"Stroke 1","mn":"ADBE Vector Graphic - Stroke","hd":false},{"ty":"tr","p":{"a":0,"k":[0,0],"ix":2},"a":{"a":0,"k":[0,0],"ix":1},"s":{"a":0,"k":[100,100],"ix":3},"r":{"a":0,"k":0,"ix":6},"o":{"a":0,"k":100,"ix":7},"sk":{"a":0,"k":0,"ix":4},"sa":{"a":0,"k":0,"ix":5},"nm":"Transform"}],"nm":"Line","np":2,"cix":2,"bm":0,"ix":1,"mn":"ADBE Vector Group","hd":false},{"ty":"gr","it":[{"ind":0,"ty":"sh","ix":1,"ks":{"a":0,"k":{"i":[[0,0],[0,0]],"o":[[0,0],[0,0]],"v":[[-50.491,-72.039],[-50.491,-16.187]],"c":false},"ix":2},"nm":"Path 1","mn":"ADBE Vector Shape - Group","hd":false},{"ty":"st","c":{"a":0,"k":[1,1,1,1],"ix":3},"o":{"a":0,"k":100,"ix":4},"w":{"a":0,"k":14,"ix":5},"lc":2,"lj":1,"ml":4,"bm":0,"nm":"Stroke 1","mn":"ADBE Vector Graphic - Stroke","hd":false},{"ty":"tr","p":{"a":0,"k":[0,0],"ix":2},"a":{"a":0,"k":[0,0],"ix":1},"s":{"a":0,"k":[100,100],"ix":3},"r":{"a":0,"k":0,"ix":6},"o":{"a":0,"k":100,"ix":7},"sk":{"a":0,"k":0,"ix":4},"sa":{"a":0,"k":0,"ix":5},"nm":"Transform"}],"nm":"Line","np":2,"cix":2,"bm":0,"ix":2,"mn":"ADBE Vector Group","hd":false}],"ip":0,"op":12,"st":-40,"bm":0},{"ddd":0,"ind":5,"ty":4,"nm":"Top","parent":6,"sr":1,"ks":{"o":{"a":0,"k":100,"ix":11},"r":{"a":0,"k":0,"ix":10},"p":{"a":1,"k":[{"i":{"x":0.29,"y":1},"o":{"x":0.4,"y":0},"t":15.756,"s":[107.25,-97.959,0],"to":[0,0,0],"ti":[0,0,0]},{"i":{"x":0,"y":1},"o":{"x":0.3,"y":0},"t":25.023,"s":[21.044,-7.523,0],"to":[0,0,0],"ti":[0,0,0]},{"i":{"x":0,"y":1},"o":{"x":0.167,"y":0},"t":33,"s":[63.409,-54.825,0],"to":[0,0,0],"ti":[0,0,0]},{"t":36,"s":[63.826,-55.034,0]}],"ix":2},"a":{"a":0,"k":[63.409,-54.825,0],"ix":1},"s":{"a":0,"k":[100,100,100],"ix":6}},"ao":0,"shapes":[{"ty":"gr","it":[{"ind":0,"ty":"sh","ix":1,"ks":{"a":1,"k":[{"i":{"x":0.29,"y":1},"o":{"x":0.4,"y":0},"t":17.609,"s":[{"i":[[-1.292,19.708],[-12.097,12.979],[-9.767,-0.419],[0.287,-9.878],[10.245,-10.617],[10.387,-0.012]],"o":[[0.524,-7.992],[12.097,-12.979],[10.493,0.45],[-0.363,12.492],[-10.795,11.186],[-8.234,0.01]],"v":[[36.438,-53.239],[50.003,-81.736],[81.802,-94.858],[105.468,-70.595],[90.399,-39.487],[60.903,-26.81]],"c":true}]},{"i":{"x":0.833,"y":1},"o":{"x":0.3,"y":0},"t":24.098,"s":[{"i":[[0,0],[-5.789,2.953],[-5.107,-2.041],[-3.199,-9.875],[2.869,-4.743],[0,0]],"o":[[0,0],[7.186,-3.665],[9.848,3.936],[2.223,6.862],[-3.729,6.165],[0,0]],"v":[[20.6,-77.99],[35.79,-93.236],[53.607,-92.45],[99.108,-48.105],[98.224,-30.203],[84.012,-15.91]],"c":true}]},{"t":33,"s":[{"i":[[0,0],[0,0],[-4.488,-4.504],[0,0],[4.488,-4.504],[0,0]],"o":[[0,0],[4.488,-4.504],[0,0],[4.488,4.504],[0,0],[0,0]],"v":[[38.156,-61.569],[53.345,-76.815],[69.598,-76.815],[85.297,-61.06],[85.297,-44.749],[70.06,-29.458]],"c":true}]}],"ix":2},"nm":"Path 1","mn":"ADBE Vector Shape - Group","hd":false},{"ty":"fl","c":{"a":0,"k":[1,1,1,1],"ix":4},"o":{"a":0,"k":100,"ix":5},"r":1,"bm":0,"nm":"Fill 1","mn":"ADBE Vector Graphic - Fill","hd":false},{"ty":"tr","p":{"a":0,"k":[0,0],"ix":2},"a":{"a":0,"k":[0,0],"ix":1},"s":{"a":0,"k":[100,100],"ix":3},"r":{"a":0,"k":0,"ix":6},"o":{"a":0,"k":100,"ix":7},"sk":{"a":0,"k":0,"ix":4},"sa":{"a":0,"k":0,"ix":5},"nm":"Transform"}],"nm":"Rectangle-Copy-3","np":2,"cix":2,"bm":0,"ix":1,"mn":"ADBE Vector Group","hd":false}],"ip":15,"op":121,"st":-25,"bm":0},{"ddd":0,"ind":6,"ty":4,"nm":"Bottom","parent":1,"sr":1,"ks":{"o":{"a":0,"k":100,"ix":11},"r":{"a":1,"k":[{"i":{"x":[0.252],"y":[1]},"o":{"x":[0.586],"y":[0]},"t":14.83,"s":[-44]},{"t":32.439453125,"s":[0]}],"ix":10},"p":{"a":1,"k":[{"i":{"x":0.3,"y":1},"o":{"x":0.3,"y":0},"t":15,"s":[-2.269,8.646,0],"to":[0,0,0],"ti":[0,0,0]},{"i":{"x":0.3,"y":1},"o":{"x":0.3,"y":0},"t":22,"s":[-5.519,42.646,0],"to":[0,0,0],"ti":[0,0,0]},{"i":{"x":0.69,"y":1},"o":{"x":0.3,"y":0},"t":31,"s":[-8.435,-5.354,0],"to":[0,0,0],"ti":[0,0,0]},{"t":36,"s":[-12.602,11.146,0]}],"ix":2},"a":{"a":0,"k":[-0.102,8.646,0],"ix":1},"s":{"a":0,"k":[100,100,100],"ix":6}},"ao":0,"shapes":[{"ty":"gr","it":[{"ind":0,"ty":"sh","ix":1,"ks":{"a":1,"k":[{"i":{"x":0.29,"y":1},"o":{"x":0.4,"y":0},"t":14.83,"s":[{"i":[[25.55,-30.97],[16.767,-8.433],[11.674,-4.106],[7.346,-0.171],[1.518,5.211],[0,0],[0,0],[-2.526,3.9],[-13.242,7.13]],"o":[[-7.407,8.979],[-8.516,4.283],[0,0],[-7.826,0.182],[-1.518,-5.211],[0,0],[1.026,-4.028],[19.583,-30.24],[23.662,-23.489]],"v":[[77.869,-19.776],[11.958,43.232],[-15.176,55.98],[-37.467,60.767],[-53.007,48.469],[-51.165,31.03],[-50.483,27.098],[-37.5,1.636],[29.389,-67.4]],"c":true}]},{"i":{"x":0.3,"y":1},"o":{"x":0.3,"y":0},"t":24.098,"s":[{"i":[[0,0],[0,0],[3.048,0],[0,0],[1.046,2.636],[0,0],[0,0],[-2.155,2.163],[0,0]],"o":[[0,0],[-2.155,2.163],[0,0],[-2.683,-0.916],[0,0],[0,0],[0,-3.059],[0,0],[0,0]],"v":[[29.961,42.238],[-20.03,80.726],[-28.156,84.104],[-56.553,70.608],[-62.138,65.022],[-78.008,38.935],[-78.008,38.935],[-74.642,30.78],[-34.754,-18.818]],"c":true}]},{"i":{"x":0.833,"y":1},"o":{"x":0.167,"y":0},"t":33,"s":[{"i":[[0,0],[0,0],[3.048,0],[0,0],[0,3.085],[0,0],[0,0],[-2.155,2.163],[0,0]],"o":[[0,0],[-2.155,2.163],[0,0],[-3.085,0],[0,0],[0,0],[0,-3.059],[0,0],[0,0]],"v":[[61.933,-21.302],[-26.266,67.23],[-34.393,70.608],[-56.553,70.608],[-62.138,65.022],[-62.138,43.874],[-62.138,43.874],[-58.772,35.719],[29.933,-53.316]],"c":true}]},{"t":36,"s":[{"i":[[0,0],[0,0],[3.048,0],[0,0],[0,3.085],[0,0],[0,0],[-2.155,2.163],[0,0]],"o":[[0,0],[-2.155,2.163],[0,0],[-3.085,0],[0,0],[0,0],[0,-3.059],[0,0],[0,0]],"v":[[61.933,-21.302],[-26.266,67.23],[-34.393,70.608],[-56.553,70.608],[-61.929,64.918],[-61.721,43.874],[-61.721,43.874],[-58.772,35.719],[29.933,-53.316]],"c":true}]}],"ix":2},"nm":"Path 1","mn":"ADBE Vector Shape - Group","hd":false},{"ty":"fl","c":{"a":0,"k":[1,1,1,1],"ix":4},"o":{"a":0,"k":100,"ix":5},"r":1,"bm":0,"nm":"Fill 1","mn":"ADBE Vector Graphic - Fill","hd":false},{"ty":"tr","p":{"a":0,"k":[0,0],"ix":2},"a":{"a":0,"k":[0,0],"ix":1},"s":{"a":0,"k":[100,100],"ix":3},"r":{"a":0,"k":0,"ix":6},"o":{"a":0,"k":100,"ix":7},"sk":{"a":0,"k":0,"ix":4},"sa":{"a":0,"k":0,"ix":5},"nm":"Transform"}],"nm":"Rectangle-Copy-3","np":2,"cix":2,"bm":0,"ix":1,"mn":"ADBE Vector Group","hd":false}],"ip":15,"op":121,"st":-25,"bm":0}],"markers":[]}